geocon/__init__.py
geocon/geocon.py
src/__init__.py
src/geocon.py
geocon-0.0.3.dist-info/LICENSE
geocon-0.0.3.dist-info/METADATA
geocon-0.0.3.dist-info/WHEEL
geocon-0.0.3.dist-info/entry_points.txt
geocon-0.0.3.dist-info/top_level.txt
geocon-0.0.3.dist-info/RECORD
