Metadata-Version: 2.1
Name: geocon
Version: 0.0.3
Summary: A UTM -> Lat/Long (or vice versa) converter.
Home-page: https://github.com/pekebuda/utm-lat-long-converter-python
Author: Fernando Diaz Laclaustra
Author-email: peke_buda@hotmail.com
License: MIT
Keywords: hello world insanely useful
Platform: UNKNOWN
Classifier: Development Status :: 4 - Beta
Classifier: Intended Audience :: Developers
Classifier: License :: OSI Approved :: MIT License
Classifier: Programming Language :: Python :: 2
Classifier: Programming Language :: Python :: 2.7
Classifier: Programming Language :: Python :: 3
Classifier: Programming Language :: Python :: 3.4
